stylegan2_pytorch/__init__.py
stylegan2_pytorch/cli.py
stylegan2_pytorch/diff_augment.py
stylegan2_pytorch/stylegan2_pytorch.py
stylegan2_pytorch/version.py
stylegan2_pytorch-1.9.0.dist-info/LICENSE
stylegan2_pytorch-1.9.0.dist-info/METADATA
stylegan2_pytorch-1.9.0.dist-info/WHEEL
stylegan2_pytorch-1.9.0.dist-info/entry_points.txt
stylegan2_pytorch-1.9.0.dist-info/top_level.txt
stylegan2_pytorch-1.9.0.dist-info/RECORD
